{"text": "\n1. Sin asdub kohttu laua jure Herküllasd Kurrema Hanso poeg Juhan Luik ja pärrib Herkülasd Raeja saana ehittamisese raha Rein Kingisseba kääsd. Hans Luik ja Rein Kingisseb on setta sauna seildsis ehittant ja Hansu poeg Juhan Luik pärrib tööd mis issa ehittas ja mis ka Rein Kingsseb ja Hans Luik on poilikit olnut Diina Orrab kääsd ja saun maksis nelli küllimitu rukkit mis nemat oisdsit.\n\nEj wõi wala kohus seda aisja seledda peab kihelkona kohtust kuulama.\n\npea kohtumees Jaan Ausmees XXX\n\nkõrwamees Mart Ausmees XXX\n\nkõrwamees Jaan Rebane XXX\n\n\n", "meta": {"origin_directory": "vallakohus_neljas/", "filename": "Harju_Juuru_Juuru_id20262_1868a.json"}, "layers": [{"name": "gold_ner", "attributes": ["nertag"], "parent": null, "enveloping": null, "ambiguous": false, "serialisation_module": null, "meta": {}, "spans": [{"base_span": [31, 41], "annotations": [{"nertag": "LOC"}]}, {"base_span": [42, 49], "annotations": [{"nertag": "LOC_ORG"}]}, {"base_span": [50, 55], "annotations": [{"nertag": "PER"}]}, {"base_span": [61, 71], "annotations": [{"nertag": "PER"}]}, {"base_span": [82, 91], "annotations": [{"nertag": "LOC"}]}, {"base_span": [92, 103], "annotations": [{"nertag": "LOC_ORG"}]}, {"base_span": [122, 137], "annotations": [{"nertag": "PER"}]}, {"base_span": [145, 154], "annotations": [{"nertag": "PER"}]}, {"base_span": [158, 172], "annotations": [{"nertag": "PER"}]}, {"base_span": [209, 214], "annotations": [{"nertag": "PER"}]}, {"base_span": [220, 230], "annotations": [{"nertag": "PER"}]}, {"base_span": [270, 283], "annotations": [{"nertag": "PER"}]}, {"base_span": [287, 296], "annotations": [{"nertag": "PER"}]}, {"base_span": [315, 326], "annotations": [{"nertag": "PER"}]}, {"base_span": [475, 487], "annotations": [{"nertag": "PER"}]}, {"base_span": [503, 515], "annotations": [{"nertag": "PER"}]}, {"base_span": [531, 542], "annotations": [{"nertag": "PER"}]}]}, {"name": "gold_wordner", "attributes": ["nertag"], "parent": null, "enveloping": null, "ambiguous": false, "serialisation_module": null, "meta": {}, "spans": [{"base_span": [1, 3], "annotations": [{"nertag": "O"}]}, {"base_span": [4, 7], "annotations": [{"nertag": "O"}]}, {"base_span": [8, 13], "annotations": [{"nertag": "O"}]}, {"base_span": [14, 20], "annotations": [{"nertag": "O"}]}, {"base_span": [21, 25], "annotations": [{"nertag": "O"}]}, {"base_span": [26, 30], "annotations": [{"nertag": "O"}]}, {"base_span": [31, 41], "annotations": [{"nertag": "B-LOC"}]}, {"base_span": [42, 49], "annotations": [{"nertag": "B-LOC_ORG"}]}, {"base_span": [50, 55], "annotations": [{"nertag": "B-PER"}]}, {"base_span": [56, 60], "annotations": [{"nertag": "O"}]}, {"base_span": [61, 66], "annotations": [{"nertag": "B-PER"}]}, {"base_span": [67, 71], "annotations": [{"nertag": "I-PER"}]}, {"base_span": [72, 74], "annotations": [{"nertag": "O"}]}, {"base_span": [75, 81], "annotations": [{"nertag": "O"}]}, {"base_span": [82, 91], "annotations": [{"nertag": "B-LOC"}]}, {"base_span": [92, 97], "annotations": [{"nertag": "B-LOC_ORG"}]}, {"base_span": [98, 103], "annotations": [{"nertag": "I-LOC_ORG"}]}, {"base_span": [104, 116], "annotations": [{"nertag": "O"}]}, {"base_span": [117, 121], "annotations": [{"nertag": "O"}]}, {"base_span": [122, 126], "annotations": [{"nertag": "B-PER"}]}, {"base_span": [127, 137], "annotations": [{"nertag": "I-PER"}]}, {"base_span": [138, 143], "annotations": [{"nertag": "O"}]}, {"base_span": [143, 144], "annotations": [{"nertag": "O"}]}, {"base_span": [145, 149], "annotations": [{"nertag": "B-PER"}]}, {"base_span": [150, 154], "annotations": [{"nertag": "I-PER"}]}, {"base_span": [155, 157], "annotations": [{"nertag": "O"}]}, {"base_span": [158, 162], "annotations": [{"nertag": "B-PER"}]}, {"base_span": [163, 172], "annotations": [{"nertag": "I-PER"}]}, {"base_span": [173, 175], "annotations": [{"nertag": "O"}]}, {"base_span": [176, 181], "annotations": [{"nertag": "O"}]}, {"base_span": [182, 187], "annotations": [{"nertag": "O"}]}, {"base_span": [188, 196], "annotations": [{"nertag": "O"}]}, {"base_span": [197, 205], "annotations": [{"nertag": "O"}]}, {"base_span": [206, 208], "annotations": [{"nertag": "O"}]}, {"base_span": [209, 214], "annotations": [{"nertag": "B-PER"}]}, {"base_span": [215, 219], "annotations": [{"nertag": "O"}]}, {"base_span": [220, 225], "annotations": [{"nertag": "B-PER"}]}, {"base_span": [226, 230], "annotations": [{"nertag": "I-PER"}]}, {"base_span": [231, 237], "annotations": [{"nertag": "O"}]}, {"base_span": [238, 242], "annotations": [{"nertag": "O"}]}, {"base_span": [243, 246], "annotations": [{"nertag": "O"}]}, {"base_span": [247, 251], "annotations": [{"nertag": "O"}]}, {"base_span": [252, 259], "annotations": [{"nertag": "O"}]}, {"base_span": [260, 262], "annotations": [{"nertag": "O"}]}, {"base_span": [263, 266], "annotations": [{"nertag": "O"}]}, {"base_span": [267, 269], "annotations": [{"nertag": "O"}]}, {"base_span": [270, 274], "annotations": [{"nertag": "B-PER"}]}, {"base_span": [275, 283], "annotations": [{"nertag": "I-PER"}]}, {"base_span": [284, 286], "annotations": [{"nertag": "O"}]}, {"base_span": [287, 291], "annotations": [{"nertag": "B-PER"}]}, {"base_span": [292, 296], "annotations": [{"nertag": "I-PER"}]}, {"base_span": [297, 299], "annotations": [{"nertag": "O"}]}, {"base_span": [300, 308], "annotations": [{"nertag": "O"}]}, {"base_span": [309, 314], "annotations": [{"nertag": "O"}]}, {"base_span": [315, 320], "annotations": [{"nertag": "B-PER"}]}, {"base_span": [321, 326], "annotations": [{"nertag": "I-PER"}]}, {"base_span": [327, 332], "annotations": [{"nertag": "O"}]}, {"base_span": [333, 335], "annotations": [{"nertag": "O"}]}, {"base_span": [336, 340], "annotations": [{"nertag": "O"}]}, {"base_span": [341, 347], "annotations": [{"nertag": "O"}]}, {"base_span": [348, 353], "annotations": [{"nertag": "O"}]}, {"base_span": [354, 363], "annotations": [{"nertag": "O"}]}, {"base_span": [364, 370], "annotations": [{"nertag": "O"}]}, {"base_span": [371, 374], "annotations": [{"nertag": "O"}]}, {"base_span": [375, 380], "annotations": [{"nertag": "O"}]}, {"base_span": [381, 388], "annotations": [{"nertag": "O"}]}, {"base_span": [388, 389], "annotations": [{"nertag": "O"}]}, {"base_span": [391, 393], "annotations": [{"nertag": "O"}]}, {"base_span": [394, 397], "annotations": [{"nertag": "O"}]}, {"base_span": [398, 402], "annotations": [{"nertag": "O"}]}, {"base_span": [403, 408], "annotations": [{"nertag": "O"}]}, {"base_span": [409, 413], "annotations": [{"nertag": "O"}]}, {"base_span": [414, 419], "annotations": [{"nertag": "O"}]}, {"base_span": [420, 427], "annotations": [{"nertag": "O"}]}, {"base_span": [428, 432], "annotations": [{"nertag": "O"}]}, {"base_span": [433, 442], "annotations": [{"nertag": "O"}]}, {"base_span": [443, 450], "annotations": [{"nertag": "O"}]}, {"base_span": [451, 458], "annotations": [{"nertag": "O"}]}, {"base_span": [458, 459], "annotations": [{"nertag": "O"}]}, {"base_span": [461, 464], "annotations": [{"nertag": "O"}]}, {"base_span": [465, 474], "annotations": [{"nertag": "O"}]}, {"base_span": [475, 479], "annotations": [{"nertag": "B-PER"}]}, {"base_span": [480, 487], "annotations": [{"nertag": "I-PER"}]}, {"base_span": [488, 491], "annotations": [{"nertag": "O"}]}, {"base_span": [493, 502], "annotations": [{"nertag": "O"}]}, {"base_span": [503, 507], "annotations": [{"nertag": "B-PER"}]}, {"base_span": [508, 515], "annotations": [{"nertag": "I-PER"}]}, {"base_span": [516, 519], "annotations": [{"nertag": "O"}]}, {"base_span": [521, 530], "annotations": [{"nertag": "O"}]}, {"base_span": [531, 535], "annotations": [{"nertag": "B-PER"}]}, {"base_span": [536, 542], "annotations": [{"nertag": "I-PER"}]}, {"base_span": [543, 546], "annotations": [{"nertag": "O"}]}]}]}