{"text": "\nUellewannimmitud Kohtomehhe ja Wannembad wallitsiwa tämbatsel päiwal se töises Walla Nössnapannejas se Wilpo Jaani poega Kusta Torg; Se ettekutsutud, wõttis sedda Ammetid hoolegapidada ja lubbasid Wallawannemba ja Wörmündre selle eest Kusta Torga nekruti Loosi Wõtmissest prii jätta, se om et temma ei pruki loosi tõmmata.\n\nEt se õige om, tunnistawa:\n\nWallawannemb Jaan Koor XXX\n\nWörmünder Hindrik Sikkut XXX\n\nWörmünder Jakob Naggel XXX\n\nPäkohtomees Peter Issakson XXX\n\nKohtomees Johan Laan XXX\n\nKohtomees Peter Akkert XXX\n\nKohtomees Josep Adoson XXX\n\nKusta Torg XXX\n\n\n", "meta": {"origin_directory": "vallakohus_kolmas/", "filename": "Tartu_V6nnu_Ahja_id22375_1869a.json"}, "layers": [{"name": "gold_ner", "attributes": ["nertag"], "parent": null, "enveloping": null, "ambiguous": false, "serialisation_module": null, "meta": {}, "spans": [{"base_span": [104, 109], "annotations": [{"nertag": "LOC_ORG"}]}, {"base_span": [110, 115], "annotations": [{"nertag": "PER"}]}, {"base_span": [122, 132], "annotations": [{"nertag": "PER"}]}, {"base_span": [236, 247], "annotations": [{"nertag": "PER"}]}, {"base_span": [366, 375], "annotations": [{"nertag": "PER"}]}, {"base_span": [391, 405], "annotations": [{"nertag": "PER"}]}, {"base_span": [421, 433], "annotations": [{"nertag": "PER"}]}, {"base_span": [451, 465], "annotations": [{"nertag": "PER"}]}, {"base_span": [481, 491], "annotations": [{"nertag": "PER"}]}, {"base_span": [507, 519], "annotations": [{"nertag": "PER"}]}, {"base_span": [535, 547], "annotations": [{"nertag": "PER"}]}, {"base_span": [553, 563], "annotations": [{"nertag": "PER"}]}]}, {"name": "gold_wordner", "attributes": ["nertag"], "parent": null, "enveloping": null, "ambiguous": false, "serialisation_module": null, "meta": {}, "spans": [{"base_span": [1, 17], "annotations": [{"nertag": "O"}]}, {"base_span": [18, 28], "annotations": [{"nertag": "O"}]}, {"base_span": [29, 31], "annotations": [{"nertag": "O"}]}, {"base_span": [32, 41], "annotations": [{"nertag": "O"}]}, {"base_span": [42, 52], "annotations": [{"nertag": "O"}]}, {"base_span": [53, 62], "annotations": [{"nertag": "O"}]}, {"base_span": [63, 69], "annotations": [{"nertag": "O"}]}, {"base_span": [70, 72], "annotations": [{"nertag": "O"}]}, {"base_span": [73, 79], "annotations": [{"nertag": "O"}]}, {"base_span": [80, 85], "annotations": [{"nertag": "O"}]}, {"base_span": [86, 100], "annotations": [{"nertag": "O"}]}, {"base_span": [101, 103], "annotations": [{"nertag": "O"}]}, {"base_span": [104, 109], "annotations": [{"nertag": "B-LOC_ORG"}]}, {"base_span": [110, 115], "annotations": [{"nertag": "B-PER"}]}, {"base_span": [116, 121], "annotations": [{"nertag": "O"}]}, {"base_span": [122, 127], "annotations": [{"nertag": "B-PER"}]}, {"base_span": [128, 132], "annotations": [{"nertag": "I-PER"}]}, {"base_span": [132, 133], "annotations": [{"nertag": "O"}]}, {"base_span": [134, 136], "annotations": [{"nertag": "O"}]}, {"base_span": [137, 149], "annotations": [{"nertag": "O"}]}, {"base_span": [149, 150], "annotations": [{"nertag": "O"}]}, {"base_span": [151, 157], "annotations": [{"nertag": "O"}]}, {"base_span": [158, 163], "annotations": [{"nertag": "O"}]}, {"base_span": [164, 171], "annotations": [{"nertag": "O"}]}, {"base_span": [172, 185], "annotations": [{"nertag": "O"}]}, {"base_span": [186, 188], "annotations": [{"nertag": "O"}]}, {"base_span": [189, 197], "annotations": [{"nertag": "O"}]}, {"base_span": [198, 211], "annotations": [{"nertag": "O"}]}, {"base_span": [212, 214], "annotations": [{"nertag": "O"}]}, {"base_span": [215, 224], "annotations": [{"nertag": "O"}]}, {"base_span": [225, 230], "annotations": [{"nertag": "O"}]}, {"base_span": [231, 235], "annotations": [{"nertag": "O"}]}, {"base_span": [236, 241], "annotations": [{"nertag": "B-PER"}]}, {"base_span": [242, 247], "annotations": [{"nertag": "I-PER"}]}, {"base_span": [248, 255], "annotations": [{"nertag": "O"}]}, {"base_span": [256, 261], "annotations": [{"nertag": "O"}]}, {"base_span": [262, 272], "annotations": [{"nertag": "O"}]}, {"base_span": [273, 277], "annotations": [{"nertag": "O"}]}, {"base_span": [278, 283], "annotations": [{"nertag": "O"}]}, {"base_span": [283, 284], "annotations": [{"nertag": "O"}]}, {"base_span": [285, 287], "annotations": [{"nertag": "O"}]}, {"base_span": [288, 290], "annotations": [{"nertag": "O"}]}, {"base_span": [291, 293], "annotations": [{"nertag": "O"}]}, {"base_span": [294, 299], "annotations": [{"nertag": "O"}]}, {"base_span": [300, 302], "annotations": [{"nertag": "O"}]}, {"base_span": [303, 308], "annotations": [{"nertag": "O"}]}, {"base_span": [309, 314], "annotations": [{"nertag": "O"}]}, {"base_span": [315, 322], "annotations": [{"nertag": "O"}]}, {"base_span": [322, 323], "annotations": [{"nertag": "O"}]}, {"base_span": [325, 327], "annotations": [{"nertag": "O"}]}, {"base_span": [328, 330], "annotations": [{"nertag": "O"}]}, {"base_span": [331, 335], "annotations": [{"nertag": "O"}]}, {"base_span": [336, 338], "annotations": [{"nertag": "O"}]}, {"base_span": [338, 339], "annotations": [{"nertag": "O"}]}, {"base_span": [340, 350], "annotations": [{"nertag": "O"}]}, {"base_span": [350, 351], "annotations": [{"nertag": "O"}]}, {"base_span": [353, 365], "annotations": [{"nertag": "O"}]}, {"base_span": [366, 370], "annotations": [{"nertag": "B-PER"}]}, {"base_span": [371, 375], "annotations": [{"nertag": "I-PER"}]}, {"base_span": [376, 379], "annotations": [{"nertag": "O"}]}, {"base_span": [381, 390], "annotations": [{"nertag": "O"}]}, {"base_span": [391, 398], "annotations": [{"nertag": "B-PER"}]}, {"base_span": [399, 405], "annotations": [{"nertag": "I-PER"}]}, {"base_span": [406, 409], "annotations": [{"nertag": "O"}]}, {"base_span": [411, 420], "annotations": [{"nertag": "O"}]}, {"base_span": [421, 426], "annotations": [{"nertag": "B-PER"}]}, {"base_span": [427, 433], "annotations": [{"nertag": "I-PER"}]}, {"base_span": [434, 437], "annotations": [{"nertag": "O"}]}, {"base_span": [439, 450], "annotations": [{"nertag": "O"}]}, {"base_span": [451, 456], "annotations": [{"nertag": "B-PER"}]}, {"base_span": [457, 465], "annotations": [{"nertag": "I-PER"}]}, {"base_span": [466, 469], "annotations": [{"nertag": "O"}]}, {"base_span": [471, 480], "annotations": [{"nertag": "O"}]}, {"base_span": [481, 486], "annotations": [{"nertag": "B-PER"}]}, {"base_span": [487, 491], "annotations": [{"nertag": "I-PER"}]}, {"base_span": [492, 495], "annotations": [{"nertag": "O"}]}, {"base_span": [497, 506], "annotations": [{"nertag": "O"}]}, {"base_span": [507, 512], "annotations": [{"nertag": "B-PER"}]}, {"base_span": [513, 519], "annotations": [{"nertag": "I-PER"}]}, {"base_span": [520, 523], "annotations": [{"nertag": "O"}]}, {"base_span": [525, 534], "annotations": [{"nertag": "O"}]}, {"base_span": [535, 540], "annotations": [{"nertag": "B-PER"}]}, {"base_span": [541, 547], "annotations": [{"nertag": "I-PER"}]}, {"base_span": [548, 551], "annotations": [{"nertag": "O"}]}, {"base_span": [553, 558], "annotations": [{"nertag": "B-PER"}]}, {"base_span": [559, 563], "annotations": [{"nertag": "I-PER"}]}, {"base_span": [564, 567], "annotations": [{"nertag": "O"}]}]}]}