{"text": "\nAndres Kolk Wastse Koiola wallast om tellino Jurri paewast 1866 Rappina moisa monakas, temma saab moisan korter 1 wakka alla maad ja üttel lehmal põhko ilma massuta.\n\nMonaka kohhus om igga paew moisa töle tulla, suwwe töö palk om 25 kopik talwe 20 kopik naese kohhus om suwe aal pool aig moisa tö pale tulla, talwe 1 paew näddalas, naise to palk om 15 kopik paewas, tüttar Mai 16 aasta wanna käib igga päew moisa töle ja saab ka 15 kopik paewa palk. Keik jalla töö ristad, kui kirwes, wikkad, rehhe, loop, wiggel peab monakas henda kaest liggi toma, kui suure saksamaa wikkatega saa nitma, siis saa mehhel kui naisel 3 kopik igga päew palka paele massatu.\n\nMona rukki wak massab 135 kopik, surmed 1/24 matt 6 kopik.\n\n5 süld puid sawa monakal tarre mannu weeta ja maswa 5 rubla.\n\n1 wakkamaa haina teggemise palk om 40 kopik kui haina om kuhja pantu.\n\n1 wakkamaa wilja leikus 75 kopik kui kokko om panto. 1 süld krhwi leikus 5 jalg pält lai, pohjast 2 jalg lai 1 1/2 jalg süggaw massab 3 kopik\n\n1 süld krawi pält 6 jalg lai 2 jalg süggaw massab 4 kopik. labbi motsa massab igga suld 1 kopik kallim, Keik krono ja walla massud massab monakas ommast palgast.\n\nKui moisa herr ehk monakas töisel aastal ei tahha sedda kontrakti eddesi piddada, siis om vaja enne Juuli ülles ütelda, kui mitte herr ega monaks ülles es olle üttelnu, siis lät to samma lepmine ni kui siin om kirjotu töise aasta päl eddesi.\n\nSel 8 Künlakuu paewal 1866\n\nAndres Kolk  XXX\n\n\n", "meta": {"origin_directory": "vallakohus_teine/", "filename": "V6ru_R2pina_R2pina_id12011_1866a.json"}, "layers": [{"name": "gold_ner", "attributes": ["nertag"], "parent": null, "enveloping": null, "ambiguous": false, "serialisation_module": null, "meta": {}, "spans": [{"base_span": [1, 12], "annotations": [{"nertag": "PER"}]}, {"base_span": [13, 34], "annotations": [{"nertag": "LOC_ORG"}]}, {"base_span": [65, 72], "annotations": [{"nertag": "LOC_ORG"}]}, {"base_span": [374, 377], "annotations": [{"nertag": "PER"}]}, {"base_span": [561, 569], "annotations": [{"nertag": "LOC"}]}, {"base_span": [1428, 1439], "annotations": [{"nertag": "PER"}]}]}, {"name": "gold_wordner", "attributes": ["nertag"], "parent": null, "enveloping": null, "ambiguous": false, "serialisation_module": null, "meta": {}, "spans": [{"base_span": [1, 7], "annotations": [{"nertag": "B-PER"}]}, {"base_span": [8, 12], "annotations": [{"nertag": "I-PER"}]}, {"base_span": [13, 19], "annotations": [{"nertag": "B-LOC_ORG"}]}, {"base_span": [20, 26], "annotations": [{"nertag": "I-LOC_ORG"}]}, {"base_span": [27, 34], "annotations": [{"nertag": "I-LOC_ORG"}]}, {"base_span": [35, 37], "annotations": [{"nertag": "O"}]}, {"base_span": [38, 45], "annotations": [{"nertag": "O"}]}, {"base_span": [46, 51], "annotations": [{"nertag": "O"}]}, {"base_span": [52, 59], "annotations": [{"nertag": "O"}]}, {"base_span": [60, 64], "annotations": [{"nertag": "O"}]}, {"base_span": [65, 72], "annotations": [{"nertag": "B-LOC_ORG"}]}, {"base_span": [73, 78], "annotations": [{"nertag": "O"}]}, {"base_span": [79, 86], "annotations": [{"nertag": "O"}]}, {"base_span": [86, 87], "annotations": [{"nertag": "O"}]}, {"base_span": [88, 93], "annotations": [{"nertag": "O"}]}, {"base_span": [94, 98], "annotations": [{"nertag": "O"}]}, {"base_span": [99, 105], "annotations": [{"nertag": "O"}]}, {"base_span": [106, 112], "annotations": [{"nertag": "O"}]}, {"base_span": [113, 114], "annotations": [{"nertag": "O"}]}, {"base_span": [115, 120], "annotations": [{"nertag": "O"}]}, {"base_span": [121, 125], "annotations": [{"nertag": "O"}]}, {"base_span": [126, 130], "annotations": [{"nertag": "O"}]}, {"base_span": [131, 133], "annotations": [{"nertag": "O"}]}, {"base_span": [134, 139], "annotations": [{"nertag": "O"}]}, {"base_span": [140, 146], "annotations": [{"nertag": "O"}]}, {"base_span": [147, 152], "annotations": [{"nertag": "O"}]}, {"base_span": [153, 157], "annotations": [{"nertag": "O"}]}, {"base_span": [158, 165], "annotations": [{"nertag": "O"}]}, {"base_span": [165, 166], "annotations": [{"nertag": "O"}]}, {"base_span": [168, 174], "annotations": [{"nertag": "O"}]}, {"base_span": [175, 181], "annotations": [{"nertag": "O"}]}, {"base_span": [182, 184], "annotations": [{"nertag": "O"}]}, {"base_span": [185, 189], "annotations": [{"nertag": "O"}]}, {"base_span": [190, 194], "annotations": [{"nertag": "O"}]}, {"base_span": [195, 200], "annotations": [{"nertag": "O"}]}, {"base_span": [201, 205], "annotations": [{"nertag": "O"}]}, {"base_span": [206, 211], "annotations": [{"nertag": "O"}]}, {"base_span": [211, 212], "annotations": [{"nertag": "O"}]}, {"base_span": [213, 218], "annotations": [{"nertag": "O"}]}, {"base_span": [219, 222], "annotations": [{"nertag": "O"}]}, {"base_span": [223, 227], "annotations": [{"nertag": "O"}]}, {"base_span": [228, 230], "annotations": [{"nertag": "O"}]}, {"base_span": [231, 233], "annotations": [{"nertag": "O"}]}, {"base_span": [234, 239], "annotations": [{"nertag": "O"}]}, {"base_span": [240, 245], "annotations": [{"nertag": "O"}]}, {"base_span": [246, 248], "annotations": [{"nertag": "O"}]}, {"base_span": [249, 254], "annotations": [{"nertag": "O"}]}, {"base_span": [255, 260], "annotations": [{"nertag": "O"}]}, {"base_span": [261, 267], "annotations": [{"nertag": "O"}]}, {"base_span": [268, 270], "annotations": [{"nertag": "O"}]}, {"base_span": [271, 275], "annotations": [{"nertag": "O"}]}, {"base_span": [276, 279], "annotations": [{"nertag": "O"}]}, {"base_span": [280, 284], "annotations": [{"nertag": "O"}]}, {"base_span": [285, 288], "annotations": [{"nertag": "O"}]}, {"base_span": [289, 294], "annotations": [{"nertag": "O"}]}, {"base_span": [295, 297], "annotations": [{"nertag": "O"}]}, {"base_span": [298, 302], "annotations": [{"nertag": "O"}]}, {"base_span": [303, 308], "annotations": [{"nertag": "O"}]}, {"base_span": [308, 309], "annotations": [{"nertag": "O"}]}, {"base_span": [310, 315], "annotations": [{"nertag": "O"}]}, {"base_span": [316, 317], "annotations": [{"nertag": "O"}]}, {"base_span": [318, 322], "annotations": [{"nertag": "O"}]}, {"base_span": [323, 331], "annotations": [{"nertag": "O"}]}, {"base_span": [331, 332], "annotations": [{"nertag": "O"}]}, {"base_span": [333, 338], "annotations": [{"nertag": "O"}]}, {"base_span": [339, 341], "annotations": [{"nertag": "O"}]}, {"base_span": [342, 346], "annotations": [{"nertag": "O"}]}, {"base_span": [347, 349], "annotations": [{"nertag": "O"}]}, {"base_span": [350, 352], "annotations": [{"nertag": "O"}]}, {"base_span": [353, 358], "annotations": [{"nertag": "O"}]}, {"base_span": [359, 365], "annotations": [{"nertag": "O"}]}, {"base_span": [365, 366], "annotations": [{"nertag": "O"}]}, {"base_span": [367, 373], "annotations": [{"nertag": "O"}]}, {"base_span": [374, 377], "annotations": [{"nertag": "B-PER"}]}, {"base_span": [378, 380], "annotations": [{"nertag": "O"}]}, {"base_span": [381, 386], "annotations": [{"nertag": "O"}]}, {"base_span": [387, 392], "annotations": [{"nertag": "O"}]}, {"base_span": [393, 397], "annotations": [{"nertag": "O"}]}, {"base_span": [398, 402], "annotations": [{"nertag": "O"}]}, {"base_span": [403, 407], "annotations": [{"nertag": "O"}]}, {"base_span": [408, 413], "annotations": [{"nertag": "O"}]}, {"base_span": [414, 418], "annotations": [{"nertag": "O"}]}, {"base_span": [419, 421], "annotations": [{"nertag": "O"}]}, {"base_span": [422, 426], "annotations": [{"nertag": "O"}]}, {"base_span": [427, 429], "annotations": [{"nertag": "O"}]}, {"base_span": [430, 432], "annotations": [{"nertag": "O"}]}, {"base_span": [433, 438], "annotations": [{"nertag": "O"}]}, {"base_span": [439, 444], "annotations": [{"nertag": "O"}]}, {"base_span": [445, 449], "annotations": [{"nertag": "O"}]}, {"base_span": [449, 450], "annotations": [{"nertag": "O"}]}, {"base_span": [451, 455], "annotations": [{"nertag": "O"}]}, {"base_span": [456, 461], "annotations": [{"nertag": "O"}]}, {"base_span": [462, 465], "annotations": [{"nertag": "O"}]}, {"base_span": [466, 472], "annotations": [{"nertag": "O"}]}, {"base_span": [472, 473], "annotations": [{"nertag": "O"}]}, {"base_span": [474, 477], "annotations": [{"nertag": "O"}]}, {"base_span": [478, 484], "annotations": [{"nertag": "O"}]}, {"base_span": [484, 485], "annotations": [{"nertag": "O"}]}, {"base_span": [486, 492], "annotations": [{"nertag": "O"}]}, {"base_span": [492, 493], "annotations": [{"nertag": "O"}]}, {"base_span": [494, 499], "annotations": [{"nertag": "O"}]}, {"base_span": [499, 500], "annotations": [{"nertag": "O"}]}, {"base_span": [501, 505], "annotations": [{"nertag": "O"}]}, {"base_span": [505, 506], "annotations": [{"nertag": "O"}]}, {"base_span": [507, 513], "annotations": [{"nertag": "O"}]}, {"base_span": [514, 518], "annotations": [{"nertag": "O"}]}, {"base_span": [519, 526], "annotations": [{"nertag": "O"}]}, {"base_span": [527, 532], "annotations": [{"nertag": "O"}]}, {"base_span": [533, 538], "annotations": [{"nertag": "O"}]}, {"base_span": [539, 544], "annotations": [{"nertag": "O"}]}, {"base_span": [545, 549], "annotations": [{"nertag": "O"}]}, {"base_span": [549, 550], "annotations": [{"nertag": "O"}]}, {"base_span": [551, 554], "annotations": [{"nertag": "O"}]}, {"base_span": [555, 560], "annotations": [{"nertag": "O"}]}, {"base_span": [561, 569], "annotations": [{"nertag": "B-LOC"}]}, {"base_span": [570, 579], "annotations": [{"nertag": "O"}]}, {"base_span": [580, 583], "annotations": [{"nertag": "O"}]}, {"base_span": [584, 589], "annotations": [{"nertag": "O"}]}, {"base_span": [589, 590], "annotations": [{"nertag": "O"}]}, {"base_span": [591, 595], "annotations": [{"nertag": "O"}]}, {"base_span": [596, 599], "annotations": [{"nertag": "O"}]}, {"base_span": [600, 606], "annotations": [{"nertag": "O"}]}, {"base_span": [607, 610], "annotations": [{"nertag": "O"}]}, {"base_span": [611, 617], "annotations": [{"nertag": "O"}]}, {"base_span": [618, 619], "annotations": [{"nertag": "O"}]}, {"base_span": [620, 625], "annotations": [{"nertag": "O"}]}, {"base_span": [626, 630], "annotations": [{"nertag": "O"}]}, {"base_span": [631, 635], "annotations": [{"nertag": "O"}]}, {"base_span": [636, 641], "annotations": [{"nertag": "O"}]}, {"base_span": [642, 647], "annotations": [{"nertag": "O"}]}, {"base_span": [648, 655], "annotations": [{"nertag": "O"}]}, {"base_span": [655, 656], "annotations": [{"nertag": "O"}]}, {"base_span": [658, 662], "annotations": [{"nertag": "O"}]}, {"base_span": [663, 668], "annotations": [{"nertag": "O"}]}, {"base_span": [669, 672], "annotations": [{"nertag": "O"}]}, {"base_span": [673, 679], "annotations": [{"nertag": "O"}]}, {"base_span": [680, 683], "annotations": [{"nertag": "O"}]}, {"base_span": [684, 689], "annotations": [{"nertag": "O"}]}, {"base_span": [689, 690], "annotations": [{"nertag": "O"}]}, {"base_span": [691, 697], "annotations": [{"nertag": "O"}]}, {"base_span": [698, 699], "annotations": [{"nertag": "O"}]}, {"base_span": [699, 700], "annotations": [{"nertag": "O"}]}, {"base_span": [700, 702], "annotations": [{"nertag": "O"}]}, {"base_span": [703, 707], "annotations": [{"nertag": "O"}]}, {"base_span": [708, 709], "annotations": [{"nertag": "O"}]}, {"base_span": [710, 715], "annotations": [{"nertag": "O"}]}, {"base_span": [715, 716], "annotations": [{"nertag": "O"}]}, {"base_span": [718, 719], "annotations": [{"nertag": "O"}]}, {"base_span": [720, 724], "annotations": [{"nertag": "O"}]}, {"base_span": [725, 729], "annotations": [{"nertag": "O"}]}, {"base_span": [730, 734], "annotations": [{"nertag": "O"}]}, {"base_span": [735, 742], "annotations": [{"nertag": "O"}]}, {"base_span": [743, 748], "annotations": [{"nertag": "O"}]}, {"base_span": [749, 754], "annotations": [{"nertag": "O"}]}, {"base_span": [755, 760], "annotations": [{"nertag": "O"}]}, {"base_span": [761, 763], "annotations": [{"nertag": "O"}]}, {"base_span": [764, 769], "annotations": [{"nertag": "O"}]}, {"base_span": [770, 771], "annotations": [{"nertag": "O"}]}, {"base_span": [772, 777], "annotations": [{"nertag": "O"}]}, {"base_span": [777, 778], "annotations": [{"nertag": "O"}]}, {"base_span": [780, 781], "annotations": [{"nertag": "O"}]}, {"base_span": [782, 790], "annotations": [{"nertag": "O"}]}, {"base_span": [791, 796], "annotations": [{"nertag": "O"}]}, {"base_span": [797, 806], "annotations": [{"nertag": "O"}]}, {"base_span": [807, 811], "annotations": [{"nertag": "O"}]}, {"base_span": [812, 814], "annotations": [{"nertag": "O"}]}, {"base_span": [815, 817], "annotations": [{"nertag": "O"}]}, {"base_span": [818, 823], "annotations": [{"nertag": "O"}]}, {"base_span": [824, 827], "annotations": [{"nertag": "O"}]}, {"base_span": [828, 833], "annotations": [{"nertag": "O"}]}, {"base_span": [834, 836], "annotations": [{"nertag": "O"}]}, {"base_span": [837, 842], "annotations": [{"nertag": "O"}]}, {"base_span": [843, 848], "annotations": [{"nertag": "O"}]}, {"base_span": [848, 849], "annotations": [{"nertag": "O"}]}, {"base_span": [851, 852], "annotations": [{"nertag": "O"}]}, {"base_span": [853, 861], "annotations": [{"nertag": "O"}]}, {"base_span": [862, 867], "annotations": [{"nertag": "O"}]}, {"base_span": [868, 874], "annotations": [{"nertag": "O"}]}, {"base_span": [875, 877], "annotations": [{"nertag": "O"}]}, {"base_span": [878, 883], "annotations": [{"nertag": "O"}]}, {"base_span": [884, 887], "annotations": [{"nertag": "O"}]}, {"base_span": [888, 893], "annotations": [{"nertag": "O"}]}, {"base_span": [894, 896], "annotations": [{"nertag": "O"}]}, {"base_span": [897, 902], "annotations": [{"nertag": "O"}]}, {"base_span": [902, 903], "annotations": [{"nertag": "O"}]}, {"base_span": [904, 905], "annotations": [{"nertag": "O"}]}, {"base_span": [906, 910], "annotations": [{"nertag": "O"}]}, {"base_span": [911, 916], "annotations": [{"nertag": "O"}]}, {"base_span": [917, 923], "annotations": [{"nertag": "O"}]}, {"base_span": [924, 925], "annotations": [{"nertag": "O"}]}, {"base_span": [926, 930], "annotations": [{"nertag": "O"}]}, {"base_span": [931, 935], "annotations": [{"nertag": "O"}]}, {"base_span": [936, 939], "annotations": [{"nertag": "O"}]}, {"base_span": [939, 940], "annotations": [{"nertag": "O"}]}, {"base_span": [941, 948], "annotations": [{"nertag": "O"}]}, {"base_span": [949, 950], "annotations": [{"nertag": "O"}]}, {"base_span": [951, 955], "annotations": [{"nertag": "O"}]}, {"base_span": [956, 959], "annotations": [{"nertag": "O"}]}, {"base_span": [960, 961], "annotations": [{"nertag": "O"}]}, {"base_span": [962, 963], "annotations": [{"nertag": "O"}]}, {"base_span": [963, 964], "annotations": [{"nertag": "O"}]}, {"base_span": [964, 965], "annotations": [{"nertag": "O"}]}, {"base_span": [966, 970], "annotations": [{"nertag": "O"}]}, {"base_span": [971, 977], "annotations": [{"nertag": "O"}]}, {"base_span": [978, 984], "annotations": [{"nertag": "O"}]}, {"base_span": [985, 986], "annotations": [{"nertag": "O"}]}, {"base_span": [987, 992], "annotations": [{"nertag": "O"}]}, {"base_span": [994, 995], "annotations": [{"nertag": "O"}]}, {"base_span": [996, 1000], "annotations": [{"nertag": "O"}]}, {"base_span": [1001, 1006], "annotations": [{"nertag": "O"}]}, {"base_span": [1007, 1011], "annotations": [{"nertag": "O"}]}, {"base_span": [1012, 1013], "annotations": [{"nertag": "O"}]}, {"base_span": [1014, 1018], "annotations": [{"nertag": "O"}]}, {"base_span": [1019, 1022], "annotations": [{"nertag": "O"}]}, {"base_span": [1023, 1024], "annotations": [{"nertag": "O"}]}, {"base_span": [1025, 1029], "annotations": [{"nertag": "O"}]}, {"base_span": [1030, 1036], "annotations": [{"nertag": "O"}]}, {"base_span": [1037, 1043], "annotations": [{"nertag": "O"}]}, {"base_span": [1044, 1045], "annotations": [{"nertag": "O"}]}, {"base_span": [1046, 1051], "annotations": [{"nertag": "O"}]}, {"base_span": [1051, 1052], "annotations": [{"nertag": "O"}]}, {"base_span": [1053, 1058], "annotations": [{"nertag": "O"}]}, {"base_span": [1059, 1064], "annotations": [{"nertag": "O"}]}, {"base_span": [1065, 1071], "annotations": [{"nertag": "O"}]}, {"base_span": [1072, 1076], "annotations": [{"nertag": "O"}]}, {"base_span": [1077, 1081], "annotations": [{"nertag": "O"}]}, {"base_span": [1082, 1083], "annotations": [{"nertag": "O"}]}, {"base_span": [1084, 1089], "annotations": [{"nertag": "O"}]}, {"base_span": [1090, 1096], "annotations": [{"nertag": "O"}]}, {"base_span": [1096, 1097], "annotations": [{"nertag": "O"}]}, {"base_span": [1098, 1102], "annotations": [{"nertag": "O"}]}, {"base_span": [1103, 1108], "annotations": [{"nertag": "O"}]}, {"base_span": [1109, 1111], "annotations": [{"nertag": "O"}]}, {"base_span": [1112, 1117], "annotations": [{"nertag": "O"}]}, {"base_span": [1118, 1124], "annotations": [{"nertag": "O"}]}, {"base_span": [1125, 1131], "annotations": [{"nertag": "O"}]}, {"base_span": [1132, 1139], "annotations": [{"nertag": "O"}]}, {"base_span": [1140, 1146], "annotations": [{"nertag": "O"}]}, {"base_span": [1147, 1154], "annotations": [{"nertag": "O"}]}, {"base_span": [1154, 1155], "annotations": [{"nertag": "O"}]}, {"base_span": [1157, 1160], "annotations": [{"nertag": "O"}]}, {"base_span": [1161, 1166], "annotations": [{"nertag": "O"}]}, {"base_span": [1167, 1171], "annotations": [{"nertag": "O"}]}, {"base_span": [1172, 1175], "annotations": [{"nertag": "O"}]}, {"base_span": [1176, 1183], "annotations": [{"nertag": "O"}]}, {"base_span": [1184, 1190], "annotations": [{"nertag": "O"}]}, {"base_span": [1191, 1197], "annotations": [{"nertag": "O"}]}, {"base_span": [1198, 1200], "annotations": [{"nertag": "O"}]}, {"base_span": [1201, 1206], "annotations": [{"nertag": "O"}]}, {"base_span": [1207, 1212], "annotations": [{"nertag": "O"}]}, {"base_span": [1213, 1222], "annotations": [{"nertag": "O"}]}, {"base_span": [1223, 1229], "annotations": [{"nertag": "O"}]}, {"base_span": [1230, 1237], "annotations": [{"nertag": "O"}]}, {"base_span": [1237, 1238], "annotations": [{"nertag": "O"}]}, {"base_span": [1239, 1243], "annotations": [{"nertag": "O"}]}, {"base_span": [1244, 1246], "annotations": [{"nertag": "O"}]}, {"base_span": [1247, 1251], "annotations": [{"nertag": "O"}]}, {"base_span": [1252, 1256], "annotations": [{"nertag": "O"}]}, {"base_span": [1257, 1262], "annotations": [{"nertag": "O"}]}, {"base_span": [1263, 1268], "annotations": [{"nertag": "O"}]}, {"base_span": [1269, 1275], "annotations": [{"nertag": "O"}]}, {"base_span": [1275, 1276], "annotations": [{"nertag": "O"}]}, {"base_span": [1277, 1280], "annotations": [{"nertag": "O"}]}, {"base_span": [1281, 1286], "annotations": [{"nertag": "O"}]}, {"base_span": [1287, 1291], "annotations": [{"nertag": "O"}]}, {"base_span": [1292, 1295], "annotations": [{"nertag": "O"}]}, {"base_span": [1296, 1302], "annotations": [{"nertag": "O"}]}, {"base_span": [1303, 1308], "annotations": [{"nertag": "O"}]}, {"base_span": [1309, 1311], "annotations": [{"nertag": "O"}]}, {"base_span": [1312, 1316], "annotations": [{"nertag": "O"}]}, {"base_span": [1317, 1324], "annotations": [{"nertag": "O"}]}, {"base_span": [1324, 1325], "annotations": [{"nertag": "O"}]}, {"base_span": [1326, 1330], "annotations": [{"nertag": "O"}]}, {"base_span": [1331, 1334], "annotations": [{"nertag": "O"}]}, {"base_span": [1335, 1337], "annotations": [{"nertag": "O"}]}, {"base_span": [1338, 1343], "annotations": [{"nertag": "O"}]}, {"base_span": [1344, 1351], "annotations": [{"nertag": "O"}]}, {"base_span": [1352, 1354], "annotations": [{"nertag": "O"}]}, {"base_span": [1355, 1358], "annotations": [{"nertag": "O"}]}, {"base_span": [1359, 1363], "annotations": [{"nertag": "O"}]}, {"base_span": [1364, 1366], "annotations": [{"nertag": "O"}]}, {"base_span": [1367, 1374], "annotations": [{"nertag": "O"}]}, {"base_span": [1375, 1380], "annotations": [{"nertag": "O"}]}, {"base_span": [1381, 1386], "annotations": [{"nertag": "O"}]}, {"base_span": [1387, 1390], "annotations": [{"nertag": "O"}]}, {"base_span": [1391, 1397], "annotations": [{"nertag": "O"}]}, {"base_span": [1397, 1398], "annotations": [{"nertag": "O"}]}, {"base_span": [1400, 1403], "annotations": [{"nertag": "O"}]}, {"base_span": [1404, 1405], "annotations": [{"nertag": "O"}]}, {"base_span": [1406, 1414], "annotations": [{"nertag": "O"}]}, {"base_span": [1415, 1421], "annotations": [{"nertag": "O"}]}, {"base_span": [1422, 1426], "annotations": [{"nertag": "O"}]}, {"base_span": [1428, 1434], "annotations": [{"nertag": "B-PER"}]}, {"base_span": [1435, 1439], "annotations": [{"nertag": "I-PER"}]}, {"base_span": [1441, 1444], "annotations": [{"nertag": "O"}]}]}]}